youtube_playlist_downloader/__init__.py
youtube_playlist_downloader/__main__.py
youtube_playlist_downloader/api_client.py
youtube_playlist_downloader/main.py
youtube_playlist_downloader/playlist_downloader.py
youtube_playlist_downloader-0.0.4.dist-info/LICENSE
youtube_playlist_downloader-0.0.4.dist-info/METADATA
youtube_playlist_downloader-0.0.4.dist-info/WHEEL
youtube_playlist_downloader-0.0.4.dist-info/entry_points.txt
youtube_playlist_downloader-0.0.4.dist-info/top_level.txt
youtube_playlist_downloader-0.0.4.dist-info/RECORD
