Metadata-Version: 2.1
Name: youtube-playlist-downloader
Version: 0.0.4
Summary: Python library to download youtube playlist for a user.
Home-page: https://gitlab.com/planetsoni/youtubeplaylistdownloader
Author: Krunal Soni
Author-email: krunalnsoni@gmail.com
License: Apache 2.0
Platform: UNKNOWN
Classifier: Programming Language :: Python :: 3
Classifier: License :: OSI Approved :: Apache Software License
Classifier: Operating System :: OS Independent
Requires-Python: >=3.6
Requires-Dist: google-auth-oauthlib
Requires-Dist: google-api-python-client
